stockmarketdata/__init__.py
stockmarketdata/ally.py
stockmarketdata/dl_quotes.py
stockmarketdata/examples.py
stockmarketdata-0.0.4.dist-info/LICENSE
stockmarketdata-0.0.4.dist-info/METADATA
stockmarketdata-0.0.4.dist-info/WHEEL
stockmarketdata-0.0.4.dist-info/top_level.txt
stockmarketdata-0.0.4.dist-info/RECORD
