Metadata-Version: 2.1
Name: stockmarketdata
Version: 0.0.4
Summary: Download current and historical stock quotes to CSV files. Built on the Ally, Robinhood, and AlphaVantage APIs and relies on their free keys.
Home-page: https://github.com/altctrlmm/stockmarketdata
Author: altctrlmm
Author-email: micahmrocks@gmail.com
License: UNKNOWN
Keywords: ally,robinhood,CSV,stock quotes,finance,stocks,options,trading,investing,AlphaVantage
Platform: UNKNOWN
Classifier: Programming Language :: Python :: 3
Classifier: License :: OSI Approved :: MIT License
Classifier: Operating System :: OS Independent
Requires-Python: >=3.5
